{
  "type": "crafting_shapeless",
  "ingredients": [
    {
			"item": "enchantingrunes:rune_c"
		},
		{
			"item": "enchantingrunes:rune_b"
		},
		{
			"item": "enchantingrunes:rune_e"
		},
		{
			"item": "minecraft:stone_pickaxe"
		}
	],
	"result": {
		"item": "minecraft:stone_pickaxe",
		"count": 1,
		"nbt": {
			"Damage": 1,
			"Enchantments": [
				{
					"id": "minecraft:efficiency",
					"lvl": 3
				},
				{
					"id": "minecraft:unbreaking",
					"lvl": 1
				},
				{
					"id": "minecraft:vanishing_curse",
					"lvl": 1
				}
			]
		}
	}
}
